Metadata-Version: 1.0
Name: django-subquery
Version: 1.0.3
Summary: SubQuery support in Django < 1.11
Home-page: https://github.com/schinckel/django-subquery/
Author: Matthew Schinckel
Author-email: matt@schinckel.net
License: UNKNOWN
Platform: UNKNOWN
